<?xml version="1.0" encoding="UTF-8"?>
<!-- vi: set et smarttab sw=4 tabstop=4: -->
<!--
Copyright © 2016 SNLab and others. All rights reserved.

This program and the accompanying materials are made available under the
terms of the Eclipse Public License v1.0 which accompanies this distribution,
and is available at http://www.eclipse.org/legal/epl-v10.html
-->
<features name="odl-scheduling-${project.version}" xmlns="http://karaf.apache.org/xmlns/features/v1.2.0"
  xmlns:xsi="http://www.w3.org/2001/XMLSchema-instance"
  xsi:schemaLocation="http://karaf.apache.org/xmlns/features/v1.2.0 http://karaf.apache.org/xmlns/features/v1.2.0">
  <repository>mvn:org.opendaylight.yangtools/features-yangtools/{{VERSION}}/xml/features</repository>
  <repository>mvn:org.opendaylight.controller/features-mdsal/{{VERSION}}/xml/features</repository>
  <repository>mvn:org.opendaylight.mdsal.model/features-mdsal-model/{{VERSION}}/xml/features</repository>
  <repository>mvn:org.opendaylight.netconf/features-restconf/{{VERSION}}/xml/features</repository>
  <repository>mvn:org.opendaylight.dlux/features-dlux/{{VERSION}}/xml/features</repository>
  <repository>mvn:fast/fast-system-features/1.0.3-Beryllium-SR3/xml/features</repository>
  <feature name='odl-fast-app-scheduling-api' version='${project.version}' description='OpenDaylight FAST APP:: scheduling :: api'>
    <feature version='${mdsal.model.version}'>odl-mdsal-models</feature>
    <feature version='1.0.3-Beryllium-SR3'>odl-fast-system</feature>
    <bundle>mvn:scheduling/fast-app-scheduling-api/${project.version}</bundle>
  </feature>
  <feature name='odl-fast-app-scheduling' version='${project.version}' description='OpenDaylight FAST APP:: scheduling'>
    <feature version='${mdsal.version}'>odl-mdsal-broker</feature>
    <feature version='${project.version}'>odl-fast-app-scheduling-api</feature>
    <bundle>mvn:scheduling/fast-app-scheduling-impl/${project.version}</bundle>
    <configfile finalname="${configfile.directory}/scheduling.xml">mvn:scheduling/fast-app-scheduling-impl/${project.version}/xml/config</configfile>
  </feature>

</features>
